minotaurx_hash.cp311-win_amd64.pyd
minotaurx_hash-1.0.dist-info/LICENSE
minotaurx_hash-1.0.dist-info/METADATA
minotaurx_hash-1.0.dist-info/WHEEL
minotaurx_hash-1.0.dist-info/top_level.txt
minotaurx_hash-1.0.dist-info/RECORD
